{
  "_comment": "Generated by tools/gpu_inventory/generate_gpu_manifests.py; do not edit by hand. Regenerate with: python3 tools/gpu_inventory/generate_gpu_manifests.py",
  "files": {
    "donner/editor/CompositorDebugPanel.cc": {
      "imguiWgpuTokens": [
        "ImGui_ImplWGPU_AddTexturePremultipliedAlphaRef",
        "ImGui_ImplWGPU_RemoveTexture",
        "ImGui_ImplWGPU_RemoveTexturePremultipliedAlphaRef"
      ],
      "operations": [
        "createTexture",
        "createView",
        "writeTexture"
      ],
      "sha256": "196474af5d8cfe357701ab338229ea3e10d499af7c85de5629ccf04ea938d867",
      "usesEditorWgpuDefine": true,
      "wgpuCFunctions": [
        "wgpuLabel"
      ],
      "wgpuCTypes": [
        "WGPUTextureView"
      ],
      "wgpuCppTokens": [
        "Extent3D",
        "TexelCopyBufferLayout",
        "TexelCopyTextureInfo",
        "Texture",
        "TextureAspect",
        "TextureDescriptor",
        "TextureDimension",
        "TextureFormat",
        "TextureUsage",
        "TextureView"
      ]
    },
    "donner/editor/CompositorDebugPanel.h": {
      "sha256": "579b48222a1976e06da737891a69734979867611d6180b9ebdbfcf56ef133675",
      "usesEditorWgpuDefine": true
    },
    "donner/editor/EditorShell.cc": {
      "operations": [
        "draw"
      ],
      "sha256": "c733ce3c9218339ae4a71a067e41a93cffdecba1f82943ff71cff7db0f58d8cd",
      "usesEditorWgpuDefine": true,
      "wgpuCFunctions": [
        "wgpuLifetimeBufferCreates",
        "wgpuLifetimeTextureCreates"
      ]
    },
    "donner/editor/EditorShell.h": {
      "sha256": "9921109bee80d87593bc7847bad55da1ce9abb8127e21bf329bdb50e1695d48f",
      "usesEditorWgpuDefine": true
    },
    "donner/editor/EditorShellPresentation.cc": {
      "operations": [
        "beginRenderPass",
        "createBindGroup",
        "createBuffer",
        "createCommandEncoder",
        "createView",
        "draw",
        "finish",
        "setBindGroup",
        "setPipeline",
        "setScissorRect",
        "submit",
        "writeBuffer"
      ],
      "sha256": "8f206c561c28ac53625d6a5b1022583bc1b95f11d1572cb6b1987941d5380109",
      "usesEditorWgpuDefine": true,
      "wgpuCFunctions": [
        "wgpuLabel"
      ],
      "wgpuCppTokens": [
        "BindGroupDescriptor",
        "BindGroupEntry",
        "BufferDescriptor",
        "BufferUsage",
        "CommandBuffer",
        "CommandEncoder",
        "CommandEncoderDescriptor",
        "Device",
        "LoadOp",
        "RenderPassColorAttachment",
        "RenderPassDescriptor",
        "RenderPassEncoder",
        "StoreOp",
        "TextureView"
      ]
    },
    "donner/editor/EditorShellPresentation.h": {
      "sha256": "cfce0bc97258101837aca304e9558495bf8099a106bc5e0a9294a57865cb1068",
      "usesEditorWgpuDefine": true,
      "wgpuCppTokens": [
        "BindGroup",
        "Buffer"
      ]
    },
    "donner/editor/FrameMissTelemetry.cc": {
      "sha256": "a62af66ece2bb3cd340557691cd29efe56e13163eb940adf4ad2c152ccac39e8",
      "wgpuCFunctions": [
        "wgpuLifetimeBufferCreates",
        "wgpuLifetimeTextureCreates"
      ]
    },
    "donner/editor/FrameMissTelemetry.h": {
      "sha256": "0e4de260e4e544f75ad93eb3501ffd8d22306ef10a828abe048db6fc40afa159",
      "wgpuCFunctions": [
        "wgpuLifetimeBufferCreates",
        "wgpuLifetimeTextureCreates"
      ]
    },
    "donner/editor/GlTextureCache.cc": {
      "imguiWgpuTokens": [
        "ImGui_ImplWGPU_AddTexturePremultipliedAlphaRef",
        "ImGui_ImplWGPU_RemoveTexture",
        "ImGui_ImplWGPU_RemoveTexturePremultipliedAlphaRef"
      ],
      "operations": [
        "createTexture",
        "createView",
        "writeTexture"
      ],
      "sha256": "089a2fa8aa762226a48600a89b2f69f28938528f6a9bdf534a52eb66ea24861e",
      "usesEditorWgpuDefine": true,
      "wgpuCFunctions": [
        "wgpuLabel",
        "wgpuLifetimeBufferCreates",
        "wgpuLifetimeTextureCreates"
      ],
      "wgpuCTypes": [
        "WGPUTextureView"
      ],
      "wgpuCppTokens": [
        "Extent3D",
        "TexelCopyBufferLayout",
        "TexelCopyTextureInfo",
        "Texture",
        "TextureAspect",
        "TextureDescriptor",
        "TextureDimension",
        "TextureFormat",
        "TextureUsage",
        "TextureView"
      ]
    },
    "donner/editor/GlTextureCache.h": {
      "sha256": "90e6b51e6e8afd32191b6eaa9c79f6e943800db36a9cf4bd653c5ae0f9d6578d",
      "usesEditorWgpuDefine": true,
      "wgpuCFunctions": [
        "wgpuLifetimeBufferCreates",
        "wgpuLifetimeTextureCreates"
      ]
    },
    "donner/editor/ImGuiBackendIncludes.h": {
      "sha256": "1b55e096e36e6e3c61198cc9ea83da02e1e0c29b237c27fed96b7e678268df18",
      "usesEditorWgpuDefine": true
    },
    "donner/editor/ViewportInteractionController.h": {
      "sha256": "f68976c751485abeaaee96c0272424c6d0a666434d1422ad32f8117c87ea1df0",
      "wgpuCFunctions": [
        "wgpuLifetimeBufferCreates",
        "wgpuLifetimeTextureCreates"
      ]
    },
    "donner/editor/gui/EditorWgpuSurface.h": {
      "sha256": "be60420bf199f229dd65300b9c4a15c23f51a309fc9b5a32244a2a1699779906",
      "wgpuCppTokens": [
        "Instance",
        "Surface"
      ]
    },
    "donner/editor/gui/EditorWgpuSurface_linux.cc": {
      "sha256": "5d203d54c295aa24c02d0c6eae9766570836040987015de5450afb1cfaec502a",
      "wgpuCppTokens": [
        "Default",
        "Instance",
        "Surface",
        "SurfaceDescriptor",
        "SurfaceSourceXlibWindow"
      ]
    },
    "donner/editor/gui/EditorWgpuSurface_macos.mm": {
      "sha256": "6603fe3661b869039fc45e1d6ee8dab074af3b183070b9b2bc883cf81b726cd6",
      "wgpuCppTokens": [
        "Default",
        "Instance",
        "Surface",
        "SurfaceDescriptor",
        "SurfaceSourceMetalLayer"
      ]
    },
    "donner/editor/gui/EditorWindow.cc": {
      "imguiWgpuTokens": [
        "ImGui_ImplWGPU_Init",
        "ImGui_ImplWGPU_InitInfo",
        "ImGui_ImplWGPU_NewFrame",
        "ImGui_ImplWGPU_RenderDrawData",
        "ImGui_ImplWGPU_Shutdown"
      ],
      "operations": [
        "beginRenderPass",
        "configure",
        "copyTextureToBuffer",
        "createBuffer",
        "createCommandEncoder",
        "createView",
        "finish",
        "getCapabilities",
        "getConstMappedRange",
        "getCurrentTexture",
        "getQueue",
        "mapAsync",
        "poll",
        "present",
        "requestAdapter",
        "requestDevice",
        "submit",
        "unmap"
      ],
      "sha256": "770a3a6b7f55d19cd53832af709d3d26a0d099326fe5a87c5305124c441eebb7",
      "usesEditorWgpuDefine": true,
      "wgpuCFunctions": [
        "wgpuCreateInstance",
        "wgpuDirectRenderCallback_",
        "wgpuInstanceCreateSurface",
        "wgpuLabel",
        "wgpuReadbackStats",
        "wgpuState_",
        "wgpuSurfacePresent",
        "wgpuUnderlayRenderCallback_"
      ],
      "wgpuCTypes": [
        "WGPUDevice",
        "WGPUEmscriptenSurfaceSourceCanvasHTMLSelector",
        "WGPUErrorType",
        "WGPUMapAsyncStatus",
        "WGPUMapAsyncStatus_Success",
        "WGPUStringView",
        "WGPUSurfaceDescriptor",
        "WGPUSurfaceGetCurrentTextureStatus_SuccessOptimal",
        "WGPUSurfaceGetCurrentTextureStatus_SuccessSuboptimal",
        "WGPUTextureFormat",
        "WGPUTextureFormat_BGRA8Unorm",
        "WGPUTextureFormat_RGBA8Unorm",
        "WGPUTextureUsage",
        "WGPUTextureUsage_CopySrc",
        "WGPUTextureUsage_RenderAttachment"
      ],
      "wgpuCppTokens": [
        "Adapter",
        "Buffer",
        "BufferDescriptor",
        "BufferMapCallbackInfo",
        "BufferUsage",
        "CallbackMode",
        "CommandBuffer",
        "CommandEncoder",
        "CompositeAlphaMode",
        "Default",
        "Device",
        "DeviceDescriptor",
        "Extent3D",
        "Instance",
        "LoadOp",
        "MapMode",
        "PresentMode",
        "Queue",
        "RenderPassColorAttachment",
        "RenderPassDescriptor",
        "RenderPassEncoder",
        "RequestAdapterOptions",
        "StoreOp",
        "StringView",
        "Surface",
        "SurfaceCapabilities",
        "SurfaceConfiguration",
        "SurfaceTexture",
        "TexelCopyBufferInfo",
        "TexelCopyTextureInfo",
        "Texture",
        "TextureFormat",
        "TextureUsage",
        "TextureView",
        "createInstance"
      ]
    },
    "donner/editor/gui/EditorWindow.h": {
      "sha256": "abf184715a0dddc27516a390fecdbf39b7d2e3d95a361e02026eafd10e0d8a9b",
      "usesEditorWgpuDefine": true,
      "wgpuCFunctions": [
        "wgpuDirectRenderCallback_",
        "wgpuState_",
        "wgpuUnderlayRenderCallback_"
      ],
      "wgpuCppTokens": [
        "Texture"
      ]
    },
    "donner/editor/repro/GlRnrReplay.cc": {
      "sha256": "e315f732bf6b5a6a1bc592cb26c56770f51ab83bb204ff6c31c81e0131a9e2a1",
      "usesEditorWgpuDefine": true
    },
    "donner/editor/tests/EditorRnrGlReplay.cc": {
      "sha256": "74f62d826e0b0ee7a14fe6c0403bd89f8385eecc3bf8562cccbedaf5a5a1e1da",
      "wgpuCFunctions": [
        "wgpuLifetimeBufferCreates",
        "wgpuLifetimeTextureCreates"
      ]
    },
    "donner/editor/tests/EditorShell_tests.cc": {
      "sha256": "be93cf6d1d89c97e3dde48c6692f8cfe96d9f212630d17babe26ea382ffb58c9",
      "wgpuCFunctions": [
        "wgpuLifetimeBufferCreates",
        "wgpuLifetimeTextureCreates"
      ]
    },
    "donner/editor/tests/EditorWindow_tests.cc": {
      "imguiWgpuTokens": [
        "ImGui_ImplWGPU_AddTexturePremultipliedAlphaRef",
        "ImGui_ImplWGPU_RemoveTexture",
        "ImGui_ImplWGPU_RemoveTexturePremultipliedAlphaRef"
      ],
      "operations": [
        "draw"
      ],
      "sha256": "ebd74326afa96e1815412ae1a66981f2dc5ca1d78588566ce9dc1a6fbf5339a7",
      "usesEditorWgpuDefine": true,
      "wgpuCTypes": [
        "WGPUTextureView"
      ]
    },
    "donner/editor/tests/FrameMissTelemetry_tests.cc": {
      "sha256": "3eeba44a3b342c94228046621599b445cdc25fd7094fe7610fc6fddf157cccc6",
      "wgpuCFunctions": [
        "wgpuLifetimeTextureCreates"
      ]
    },
    "donner/editor/tests/GlTextureCache_tests.cc": {
      "operations": [
        "createTexture"
      ],
      "sha256": "9cc6cc67790eb2e0a605496c9834eb6624306e049dd40db6a9a2ccb93b065e26",
      "usesEditorWgpuDefine": true,
      "wgpuCppTokens": [
        "Texture",
        "TextureDescriptor",
        "TextureDimension",
        "TextureFormat",
        "TextureUsage"
      ]
    },
    "donner/editor/tests/LayersPanel_tests.cc": {
      "sha256": "4072d66276e3c02ff6e1d10059e5b6edee02944cef5ef7cdcaa203c7ea705f29",
      "usesEditorWgpuDefine": true
    },
    "donner/editor/tests/ViewportInteractionController_tests.cc": {
      "sha256": "0d1f4a03dfa99511979f64c66ba3f1617ab30a588b432a59e773824363b34e91",
      "wgpuCFunctions": [
        "wgpuLifetimeBufferCreates",
        "wgpuLifetimeTextureCreates"
      ]
    }
  }
}
